mausoleum/__init__.py
mausoleum/__main__.py
mausoleum/_version.py
mausoleum/application.py
mausoleum/settings.toml
mausoleum/wrapper.py
mausoleum/images/__init__.py
mausoleum/images/ic_vpn_key_black_48dp_1x.png
mausoleum-0.15.0.dist-info/licenses/LICENSE
mausoleum-0.15.0.dist-info/METADATA
mausoleum-0.15.0.dist-info/WHEEL
mausoleum-0.15.0.dist-info/entry_points.txt
mausoleum-0.15.0.dist-info/top_level.txt
mausoleum-0.15.0.dist-info/RECORD
