Metadata-Version: 2.4
Name: mausoleum
Version: 0.15.0
Summary: A Python GUI, CLI, and wrapper for Tomb
Home-page: https://github.com/mandeep/Mausoleum
Author: Mandeep
License: GPLv3+
Keywords: Mausoleum
Classifier: License :: OSI Approved :: GNU General Public License v3 or later (GPLv3+)
Classifier: Programming Language :: Python :: 3.10
Classifier: Programming Language :: Python :: 3.11
Classifier: Programming Language :: Python :: 3.12
Classifier: Programming Language :: Python :: 3.13
License-File: LICENSE
Requires-Dist: appdirs
Requires-Dist: click
Requires-Dist: pytoml
Requires-Dist: pyqt5
Provides-Extra: tests
Requires-Dist: pytest; extra == "tests"
Requires-Dist: pytest-cov; extra == "tests"
Requires-Dist: pytest-qt; extra == "tests"
Requires-Dist: pytest-xvfb; extra == "tests"
Dynamic: author
Dynamic: classifier
Dynamic: description
Dynamic: description-content-type
Dynamic: home-page
Dynamic: keywords
Dynamic: license
Dynamic: license-file
Dynamic: provides-extra
Dynamic: requires-dist
Dynamic: summary
